flowmindercolors.py
flowmindercolors-1.1.dist-info/METADATA
flowmindercolors-1.1.dist-info/WHEEL
flowmindercolors-1.1.dist-info/top_level.txt
flowmindercolors-1.1.dist-info/RECORD
